animeflvV2/__init__.py
animeflvV2/animeflvV2.py
animeflvV2/exception.py
animeflvV2-0.0.7.dist-info/LICENSE
animeflvV2-0.0.7.dist-info/METADATA
animeflvV2-0.0.7.dist-info/WHEEL
animeflvV2-0.0.7.dist-info/top_level.txt
animeflvV2-0.0.7.dist-info/RECORD
